<CropBoxList name="Map"><CropBox name="Region_0"><min_pt x="0" y="0" z="0"/><max_pt x="1.5" y="0.9" z="0.45"/><rotation x="0" y="0" z="0"/> <translation x="-2.53" y="0.28" z="0.67"/></CropBox><CropBox name="Region_1"><min_pt x="0" y="0" z="0"/><max_pt x="0.9" y="1.5" z="0.45"/><rotation x="0" y="0" z="0"/> <translation x="-2.83" y="-1.35" z="0.67"/></CropBox><CropBox name="Region_2"><min_pt x="0" y="0" z="0"/><max_pt x="0.9" y="1.5" z="0.45"/><rotation x="0" y="0" z="0"/> <translation x="-2.83" y="-2.76" z="0.67"/></CropBox><CropBox name="Region_3"><min_pt x="0" y="0" z="0"/><max_pt x="0.9" y="1.5" z="0.45"/><rotation x="0" y="0" z="0"/> <translation x="-1.14" y="-2.69" z="0.67"/></CropBox><CropBox name="Region_4"><min_pt x="0" y="0" z="0"/><max_pt x="0.9" y="0.86" z="0.45"/><rotation x="0" y="0" z="0"/> <translation x="1.53" y="-1.28" z="0.67"/></CropBox><CropBox name="Region_5"><min_pt x="0" y="0" z="0"/><max_pt x="1.51" y="0.88" z="0.45"/><rotation x="0" y="0" z="0"/> <translation x="2.34" y="-1.28" z="0.67"/></CropBox><CropBox name="Region_6"><min_pt x="0" y="0" z="0"/><max_pt x="0.6" y="0.89" z="0.29"/><rotation x="0" y="0" z="0"/> <translation x="2.03" y="-0.49" z="0.07"/></CropBox><CropBox name="Region_7"><min_pt x="0" y="0" z="0"/><max_pt x="0.6" y="0.89" z="0.29"/><rotation x="0" y="0" z="0"/> <translation x="2.03" y="-0.49" z="0.48"/></CropBox><CropBox name="Region_8"><min_pt x="0" y="0" z="0"/><max_pt x="0.6" y="0.89" z="0.29"/><rotation x="0" y="0" z="0"/> <translation x="2.03" y="-0.49" z="0.87"/></CropBox><CropBox name="Region_9"><min_pt x="0" y="0" z="0"/><max_pt x="0.6" y="0.89" z="0.29"/><rotation x="0" y="0" z="0"/> <translation x="2.03" y="-0.49" z="1.25"/></CropBox><CropBox name="Region_10"><min_pt x="0" y="0" z="0"/><max_pt x="0.6" y="0.89" z="0.29"/><rotation x="0" y="0" z="0"/> <translation x="2.03" y="-0.49" z="1.63"/></CropBox><CropBox name="Region_11"><min_pt x="0" y="0" z="0"/><max_pt x="0.6" y="0.89" z="0.29"/><rotation x="0" y="0" z="0"/> <translation x="2.03" y="-0.49" z="1.94"/></CropBox><CropBox name="Region_12"><min_pt x="0" y="0" z="0"/><max_pt x="0.85" y="0.5" z="0.32"/><rotation x="0" y="0" z="0"/> <translation x="-0.73" y="2.5" z="0.5"/></CropBox><CropBox name="Region_13"><min_pt x="0" y="0" z="0"/><max_pt x="0.85" y="0.5" z="0.32"/><rotation x="0" y="0" z="0"/> <translation x="-0.73" y="2.5" z="0.805"/></CropBox><CropBox name="Region_14"><min_pt x="0" y="0" z="0"/><max_pt x="0.85" y="0.5" z="0.32"/><rotation x="0" y="0" z="0"/> <translation x="-0.73" y="2.5" z="1.155"/></CropBox><CropBox name="Region_15"><min_pt x="0" y="0" z="0"/><max_pt x="0.85" y="0.5" z="0.32"/><rotation x="0" y="0" z="0"/> <translation x="-0.73" y="2.5" z="1.51"/></CropBox></CropBoxList>